LICENSE
README.md
setup.cfg
setup.py
H_PyUtil/__init__.py
H_PyUtil/console.py
H_PyUtil/json_util.py
H_PyUtil.egg-info/PKG-INFO
H_PyUtil.egg-info/SOURCES.txt
H_PyUtil.egg-info/dependency_links.txt
H_PyUtil.egg-info/requires.txt
H_PyUtil.egg-info/top_level.txt