Metadata-Version: 2.1
Name: H-PyUtil
Version: 0.1
Summary: Package for convenient work with python
Author: Hamlet Sargsyan
Author-email: hamlets849@gmail.com
License-File: LICENSE
